pos_neg_neu_007/__init__.py
pos_neg_neu_007/pos_neg_neu_007.py
pos_neg_neu_007-0.1.1.dist-info/LICENSE.txt
pos_neg_neu_007-0.1.1.dist-info/METADATA
pos_neg_neu_007-0.1.1.dist-info/WHEEL
pos_neg_neu_007-0.1.1.dist-info/top_level.txt
pos_neg_neu_007-0.1.1.dist-info/RECORD
