Metadata-Version: 2.1
Name: pos-neg-neu-007
Version: 0.1.1
Summary: Get positive,negative response for given sentence
Home-page: UNKNOWN
Author: Ankit Srivastava 007
Author-email: ankits.7733@gmail.com
License: UNKNOWN
Platform: UNKNOWN
Classifier: Programming Language :: Python :: 3
Classifier: License :: OSI Approved :: MIT License
Classifier: Operating System :: OS Independent
Requires-Dist: textblob
Requires-Dist: nltk
